remote_docker_aws/__init__.py
remote_docker_aws/__main__.py
remote_docker_aws/cli_commands.py
remote_docker_aws/config.py
remote_docker_aws/constants.py
remote_docker_aws/core.py
remote_docker_aws/exceptions.py
remote_docker_aws/providers.py
remote_docker_aws/util.py
remote_docker_aws/sceptre/config/dev/application.yaml
remote_docker_aws/sceptre/config/dev/config.yaml
remote_docker_aws/sceptre/templates/application.yaml
remote_docker_aws-3.0.1.dist-info/LICENSE
remote_docker_aws-3.0.1.dist-info/METADATA
remote_docker_aws-3.0.1.dist-info/WHEEL
remote_docker_aws-3.0.1.dist-info/entry_points.txt
remote_docker_aws-3.0.1.dist-info/top_level.txt
remote_docker_aws-3.0.1.dist-info/RECORD
