Metadata-Version: 2.1
Name: remote-docker-aws
Version: 3.0.1
Summary: Client to control a remote-docker agent
Home-page: https://github.com/lime-green/remote-docker-aws
Author: Josh DM
License: MIT
Keywords: docker,aws,development,macos,linux
Classifier: Development Status :: 5 - Production/Stable
Classifier: Intended Audience :: Developers
Classifier: License :: OSI Approved :: MIT License
Classifier: Operating System :: OS Independent
Classifier: Programming Language :: Python
Classifier: Programming Language :: Python :: 3
Classifier: Programming Language :: Python :: 3.7
Classifier: Programming Language :: Python :: 3.8
Classifier: Programming Language :: Python :: 3.9
Classifier: Programming Language :: Python :: 3.10
Classifier: Programming Language :: Python :: 3.11
Classifier: Topic :: Software Development :: Libraries
Classifier: Topic :: Software Development :: Libraries :: Python Modules
Requires-Python: >=3.6, <4
License-File: LICENSE
Requires-Dist: boto3
Requires-Dist: sceptre (>=2.5)
Requires-Dist: click (~=8.0)
Requires-Dist: unison-gitignore (>=1.0.4)
Requires-Dist: colorlog
Provides-Extra: dev
Requires-Dist: black ; extra == 'dev'
Requires-Dist: pytest ; extra == 'dev'
Requires-Dist: flake8 ; extra == 'dev'
Requires-Dist: moto[cloudformation,ec2] ; extra == 'dev'
Requires-Dist: cryptography ; extra == 'dev'
